README.md
setup.py
nameit/__init__.py
nameit.egg-info/PKG-INFO
nameit.egg-info/SOURCES.txt
nameit.egg-info/dependency_links.txt
nameit.egg-info/top_level.txt