Metadata-Version: 2.1
Name: nameit
Version: 0.0.1
Summary: Nothing
Home-page: https://github.com/eaybek/nameit
Author: Erdem Aybek
Author-email: eaybek@gmail.com
License: UNKNOWN
Platform: UNKNOWN
Classifier: Programming Language :: Python :: 3
Classifier: License :: OSI Approved :: MIT License
Classifier: Operating System :: POSIX :: Linux
Classifier: Development Status :: 1 - Planning
Requires-Python: >=3.6
